README.rst
setup.cfg
setup.py
stacker_blueprints/__init__.py
stacker_blueprints/asg.py
stacker_blueprints/aws_lambda.py
stacker_blueprints/bastion.py
stacker_blueprints/certificate_manager.py
stacker_blueprints/cloudwatch_logs.py
stacker_blueprints/codebuild.py
stacker_blueprints/dynamodb.py
stacker_blueprints/ec2.py
stacker_blueprints/ecr.py
stacker_blueprints/ecs.py
stacker_blueprints/efs.py
stacker_blueprints/elasticsearch.py
stacker_blueprints/generic.py
stacker_blueprints/iam_roles.py
stacker_blueprints/kinesis.py
stacker_blueprints/kms.py
stacker_blueprints/network.py
stacker_blueprints/policies.py
stacker_blueprints/postgres.py
stacker_blueprints/route53.py
stacker_blueprints/s3.py
stacker_blueprints/security_rules.py
stacker_blueprints/sns.py
stacker_blueprints/sqs.py
stacker_blueprints/util.py
stacker_blueprints/vpc.py
stacker_blueprints/vpc_flow_logs.py
stacker_blueprints.egg-info/PKG-INFO
stacker_blueprints.egg-info/SOURCES.txt
stacker_blueprints.egg-info/dependency_links.txt
stacker_blueprints.egg-info/requires.txt
stacker_blueprints.egg-info/top_level.txt
stacker_blueprints/elasticache/__init__.py
stacker_blueprints/elasticache/base.py
stacker_blueprints/elasticache/redis.py
stacker_blueprints/empire/__init__.py
stacker_blueprints/empire/base.py
stacker_blueprints/empire/controller.py
stacker_blueprints/empire/daemon.py
stacker_blueprints/empire/minion.py
stacker_blueprints/empire/policies.py
stacker_blueprints/firehose/__init__.py
stacker_blueprints/firehose/base.py
stacker_blueprints/firehose/redshift.py
stacker_blueprints/firehose/s3.py
stacker_blueprints/rds/__init__.py
stacker_blueprints/rds/base.py
stacker_blueprints/rds/mysql.py
stacker_blueprints/rds/postgres.py
stacker_blueprints/rds/aurora/__init__.py
stacker_blueprints/rds/aurora/base.py
tests/__init__.py
tests/test_asg.py
tests/test_aws_lambda.py
tests/test_cloudwatch_logs.py
tests/test_efs.py
tests/test_iam_roles.py
tests/test_kinesis.py
tests/test_kms.py
tests/test_network.py
tests/test_route53.py
tests/test_vpc.py