Metadata-Version: 1.0
Name: stacker-blueprints
Version: 1.0.8
Summary: Default blueprints for stacker
Home-page: https://github.com/remind101/stacker_blueprints
Author: Michael Barrett
Author-email: loki77@gmail.com
License: New BSD license
Platform: UNKNOWN
